[
  {
    "os": "ubuntu-latest",
    "target": "build-node",
    "run_on_event": "any",
    "rust_toolchain": "nightly-2022-11-14"
  },

  {
    "os": "ubuntu-latest",
    "target": "build-runtime",
    "package": "altair-runtime",
    "run_on_event": "push",
    "rust_toolchain": "1.64.0"
  },

  {
    "os": "ubuntu-latest",
    "target": "build-runtime",
    "package": "centrifuge-runtime",
    "run_on_event": "push",
    "rust_toolchain": "1.64.0"
  },

  {
    "os": "ubuntu-latest",
    "target": "build-runtime-fast",
    "package": "altair-runtime",
    "run_on_event": "push",
    "rust_toolchain": "1.64.0"
  },

  {
    "os": "ubuntu-latest",
    "target": "build-runtime-fast",
    "package": "centrifuge-runtime",
    "run_on_event": "push",
    "rust_toolchain": "1.64.0"
  },

  {
    "os": "ubuntu-latest",
    "target": "build-runtime-testnet",
    "package": "altair-runtime",
    "run_on_event": "push",
    "rust_toolchain": "1.64.0"
  }
]
